RandomStr/__init__.py
RandomStr-0.1.11.dist-info/LICENSE
RandomStr-0.1.11.dist-info/METADATA
RandomStr-0.1.11.dist-info/WHEEL
RandomStr-0.1.11.dist-info/top_level.txt
RandomStr-0.1.11.dist-info/RECORD
