Metadata-Version: 2.1
Name: RandomStr
Version: 0.1.11
Summary: Generates a random string of your length choice.
Author-email: qloha <officialqloha@gmail.com>
Project-URL: Homepage, https://github.com/qloha/randomstr
Project-URL: Issues, https://github.com/qloha/randomstr/issues
Classifier: Programming Language :: Python :: 3
Classifier: License :: OSI Approved :: MIT License
Classifier: Operating System :: OS Independent
Requires-Python: >=3.8
License-File: LICENSE
